ess/imaging/__init__.py
ess/imaging/conversion.py
ess/imaging/data.py
ess/imaging/py.typed
ess/imaging/types.py
ess/imaging/tools/__init__.py
ess/imaging/tools/analysis.py
ess/imaging/tools/resolution.py
ess/imaging/tools/saturation.py
ess/odin/__init__.py
ess/odin/beamline.py
ess/odin/data.py
ess/odin/masking.py
ess/odin/workflows.py
ess/tbl/__init__.py
ess/tbl/data.py
ess/tbl/py.typed
ess/tbl/workflow.py
ess/ymir/data.py
ess/ymir/io.py
ess/ymir/normalize.py
ess/ymir/types.py
ess/ymir/workflow.py
essimaging-25.11.0.dist-info/licenses/LICENSE
essimaging-25.11.0.dist-info/METADATA
essimaging-25.11.0.dist-info/WHEEL
essimaging-25.11.0.dist-info/top_level.txt
essimaging-25.11.0.dist-info/RECORD
