Metadata-Version: 2.4
Name: essimaging
Version: 25.11.0
Summary: Imaging data reduction for the European Spallation Source
Author: Scipp contributors
License-Expression: BSD-3-Clause
Project-URL: Bug Tracker, https://github.com/scipp/essimaging/issues
Project-URL: Documentation, https://scipp.github.io/essimaging
Project-URL: Source, https://github.com/scipp/essimaging
Classifier: Intended Audience :: Science/Research
Classifier: Natural Language :: English
Classifier: Operating System :: OS Independent
Classifier: Programming Language :: Python :: 3
Classifier: Programming Language :: Python :: 3 :: Only
Classifier: Programming Language :: Python :: 3.11
Classifier: Programming Language :: Python :: 3.12
Classifier: Programming Language :: Python :: 3.13
Classifier: Topic :: Scientific/Engineering
Classifier: Typing :: Typed
Requires-Python: >=3.11
License-File: LICENSE
Requires-Dist: dask>=2022.1.0
Requires-Dist: graphviz
Requires-Dist: plopp[all]>=23.10.0
Requires-Dist: sciline>=23.9.1
Requires-Dist: scipp>=25.4.0
Requires-Dist: scippneutron>=24.12.0
Requires-Dist: scippnexus>=23.11.1
Requires-Dist: tifffile>=2024.7.2
Requires-Dist: essreduce>=25.11.0
Requires-Dist: scitiff>=25.7
Provides-Extra: test
Requires-Dist: pytest>=8.0; extra == "test"
Requires-Dist: pooch>=1.5; extra == "test"
Requires-Dist: tof>=25.08.0; extra == "test"
Requires-Dist: scitiff>=24.6.0; extra == "test"
Dynamic: license-file
